[
    {
        "type": "message",
        "user": "U046AEEDH",
        "text": "yesterday I learned all about what finance used to be",
        "ts": "1438348705.004907"
    },
    {
        "type": "message",
        "user": "U046AEEDH",
        "text": "the old timers told me about they used to have big cocaine parties after trading closed in the pits",
        "ts": "1438348731.004908"
    },
    {
        "type": "message",
        "user": "U046AEEDH",
        "text": "they weren't even joking man",
        "ts": "1438348737.004909"
    },
    {
        "type": "message",
        "user": "U046AEEDH",
        "text": "one of them described how traders would gamble and would put their money in a large breasted woman's cleavage to hold it there until the bet was complete",
        "ts": "1438348768.004910"
    },
    {
        "type": "message",
        "user": "U046AEEDH",
        "text": "they literally hired women to do that",
        "ts": "1438348772.004911"
    },
    {
        "type": "message",
        "user": "U046AEEDH",
        "text": "god bless",
        "ts": "1438348774.004912"
    },
    {
        "type": "message",
        "user": "U046AEEDH",
        "text": "why did it have to change?",
        "ts": "1438348777.004913"
    },
    {
        "type": "message",
        "user": "U045MBNTQ",
        "text": "because",
        "ts": "1438359317.004914"
    },
    {
        "type": "message",
        "user": "U045MBNTQ",
        "text": "times a change",
        "ts": "1438359327.004915"
    },
    {
        "type": "message",
        "user": "U046AEEDH",
        "text": ":disappointed:",
        "ts": "1438359908.004916"
    },
    {
        "type": "message",
        "user": "U046AEEDH",
        "text": "times are a-changing for me to",
        "ts": "1438359915.004917"
    },
    {
        "type": "message",
        "user": "U046AEEDH",
        "text": "switched from eclipse to intellij today",
        "ts": "1438359922.004918"
    },
    {
        "type": "message",
        "user": "U045MBNTQ",
        "text": "why",
        "ts": "1438359993.004919"
    },
    {
        "type": "message",
        "user": "U045MBNTQ",
        "text": "would you use eclipse...",
        "ts": "1438359995.004920"
    },
    {
        "type": "message",
        "user": "U045MBNTQ",
        "text": "are you masochistic?",
        "ts": "1438360005.004921"
    },
    {
        "type": "message",
        "user": "U045MBFTN",
        "text": "Lelzzz",
        "ts": "1438360061.004922"
    },
    {
        "type": "message",
        "user": "U045MBFTN",
        "text": "Just use notepad",
        "ts": "1438360067.004923"
    },
    {
        "type": "message",
        "user": "U046AEEDH",
        "text": "because I do a lot of java development",
        "ts": "1438360126.004924"
    },
    {
        "type": "message",
        "user": "U046AEEDH",
        "text": "and java development in vim is kinda sucky",
        "edited": {
            "user": "U046AEEDH",
            "ts": "1438360133.000000"
        },
        "ts": "1438360131.004925"
    },
    {
        "type": "message",
        "user": "U046AEEDH",
        "text": "and I was used to eclipse and not to intellij",
        "ts": "1438360140.004927"
    },
    {
        "type": "message",
        "user": "U046AEEDH",
        "text": "eclipse isn't terrible gais :disappointed:",
        "ts": "1438360150.004928"
    },
    {
        "type": "message",
        "user": "U045MBNTQ",
        "text": "it is.",
        "ts": "1438360189.004929"
    },
    {
        "type": "message",
        "user": "U045MBNTQ",
        "text": "dont lie to yourself...",
        "ts": "1438360193.004930"
    },
    {
        "type": "message",
        "user": "U045MBNTQ",
        "text": "and i agree that java development in vim is sucky",
        "ts": "1438360201.004931"
    },
    {
        "type": "message",
        "user": "U045MBNTQ",
        "text": "but i always just use intellij",
        "ts": "1438360208.004932"
    },
    {
        "type": "message",
        "user": "U045MBNTQ",
        "text": "with vim plugins",
        "ts": "1438360210.004933"
    },
    {
        "type": "message",
        "user": "U045MBNTQ",
        "text": "we only use jetbrains at square lol",
        "ts": "1438360225.004934"
    },
    {
        "type": "message",
        "user": "U045MBNTQ",
        "text": "jetbrains + xcode",
        "ts": "1438360227.004935"
    },
    {
        "type": "message",
        "user": "U045MBNTQ",
        "text": "because...",
        "ts": "1438360228.004936"
    },
    {
        "type": "message",
        "user": "U045MBNTQ",
        "text": "nothing else does obj-c",
        "ts": "1438360231.004937"
    },
    {
        "type": "message",
        "user": "U045MBNTQ",
        "text": "yay",
        "ts": "1438360231.004938"
    },
    {
        "type": "message",
        "user": "U045MBNTQ",
        "text": "but a lot of ruby and front end eng",
        "ts": "1438360246.004939"
    },
    {
        "type": "message",
        "user": "U045MBNTQ",
        "text": "likes to use sublime text",
        "ts": "1438360248.004940"
    },
    {
        "type": "message",
        "user": "U045MBNTQ",
        "text": "for whatever fuckin reason",
        "ts": "1438360252.004941"
    },
    {
        "type": "message",
        "user": "U03UNR40S",
        "text": "all about <http:\/\/atom.io|atom.io> :)",
        "ts": "1438360295.004942"
    },
    {
        "type": "message",
        "user": "U045MBNTQ",
        "text": "ive never used it",
        "ts": "1438360307.004943"
    },
    {
        "type": "message",
        "user": "U045MBNTQ",
        "text": "how is it",
        "ts": "1438360308.004944"
    },
    {
        "type": "message",
        "user": "U045MBNTQ",
        "text": ":disappointed:",
        "ts": "1438360637.004945"
    },
    {
        "type": "message",
        "user": "U045MBNTQ",
        "text": "guess its time to read on the bart no",
        "ts": "1438360647.004946"
    },
    {
        "type": "message",
        "user": "U045MBNTQ",
        "text": "now*",
        "ts": "1438360648.004947"
    },
    {
        "type": "message",
        "user": "U045T05DE",
        "text": "I do all my work in nano",
        "ts": "1438360793.004948"
    },
    {
        "type": "message",
        "user": "U045T05DE",
        "text": "The godliest text editor NA",
        "ts": "1438360807.004949"
    },
    {
        "type": "message",
        "user": "U045MBFTN",
        "text": "<@U03UNR40S>: are you actually using <http:\/\/atom.io|atom.io>?",
        "ts": "1438361316.004950"
    },
    {
        "type": "message",
        "user": "U046AEEDH",
        "text": "drinking every day has given me the shits",
        "ts": "1438361689.004951"
    },
    {
        "type": "message",
        "user": "U046AEEDH",
        "text": ":confused:",
        "ts": "1438361691.004952"
    },
    {
        "type": "message",
        "user": "U045MBNTQ",
        "text": "wut",
        "ts": "1438363359.004953"
    },
    {
        "type": "message",
        "user": "U045MBNTQ",
        "text": "only beer right?",
        "ts": "1438363364.004954"
    },
    {
        "type": "message",
        "user": "U045MBNTQ",
        "text": "beer help you poop better :simple_smile:",
        "ts": "1438363368.004955"
    },
    {
        "type": "message",
        "user": "U046AEEDH",
        "text": "if by better you mean \"more\"",
        "ts": "1438363388.004956"
    },
    {
        "type": "message",
        "user": "U045MBNTQ",
        "text": "like",
        "ts": "1438363417.004957"
    },
    {
        "type": "message",
        "user": "U046AEEDH",
        "text": "and if by \"more\" I'm implying \"liquid jet fuel that ignites as soon as it contacts an oxygen rich environment such as the local atmosphere in the toilet\"",
        "ts": "1438363419.004958"
    },
    {
        "type": "message",
        "user": "U045MBNTQ",
        "text": "i poop more easily",
        "ts": "1438363421.004959"
    },
    {
        "type": "message",
        "user": "U046AEEDH",
        "text": "then yes",
        "ts": "1438363422.004960"
    },
    {
        "type": "message",
        "user": "U045MBNTQ",
        "text": "oh",
        "ts": "1438363425.004961"
    },
    {
        "type": "message",
        "user": "U045MBNTQ",
        "text": "no",
        "ts": "1438363427.004962"
    },
    {
        "type": "message",
        "user": "U045MBNTQ",
        "text": "stop drinking vodka",
        "ts": "1438363430.004963"
    },
    {
        "type": "message",
        "user": "U046AEEDH",
        "text": "it's been a mix of beer and hard liquor",
        "ts": "1438363441.004964"
    },
    {
        "type": "message",
        "user": "U045MBNTQ",
        "text": "mixed drinks is bad for you",
        "ts": "1438363444.004965"
    },
    {
        "type": "message",
        "user": "U045MBNTQ",
        "text": "only drink beer",
        "ts": "1438363448.004966"
    },
    {
        "type": "message",
        "user": "U046AEEDH",
        "text": "lel",
        "ts": "1438363452.004967"
    },
    {
        "type": "message",
        "user": "U045MBNTQ",
        "text": "beer and whiskey",
        "ts": "1438363456.004968"
    },
    {
        "type": "message",
        "user": "U046AEEDH",
        "text": "the shits aren't honestly that bad at all",
        "ts": "1438363457.004969"
    },
    {
        "type": "message",
        "user": "U046AEEDH",
        "text": "just takes a bit longer to fully evacuate the bowels",
        "ts": "1438363468.004970"
    },
    {
        "type": "message",
        "user": "U045MBNTQ",
        "text": "oh :disappointed:",
        "ts": "1438363497.004971"
    },
    {
        "type": "message",
        "user": "U045MBNTQ",
        "text": "i guess i don't drink enough anymore",
        "ts": "1438363503.004972"
    },
    {
        "type": "message",
        "user": "U045MBNTQ",
        "text": "to have this happen to me",
        "ts": "1438363507.004973"
    },
    {
        "type": "message",
        "user": "U045MBNTQ",
        "text": "seriously though",
        "ts": "1438363513.004974"
    },
    {
        "type": "message",
        "user": "U045MBNTQ",
        "text": "next tie",
        "ts": "1438363514.004975"
    },
    {
        "type": "message",
        "user": "U045MBNTQ",
        "text": "time",
        "ts": "1438363515.004976"
    },
    {
        "type": "message",
        "user": "U045MBNTQ",
        "text": "only drink beer",
        "ts": "1438363516.004977"
    },
    {
        "type": "message",
        "user": "U045MBNTQ",
        "text": "then in the mornings",
        "ts": "1438363518.004978"
    },
    {
        "type": "message",
        "user": "U045MBNTQ",
        "text": "you will have great beer shits",
        "ts": "1438363522.004979"
    },
    {
        "type": "message",
        "user": "U045MBNTQ",
        "text": "it just comes out",
        "ts": "1438363523.004980"
    },
    {
        "type": "message",
        "user": "U045MBNTQ",
        "text": "and it should be solid",
        "ts": "1438363527.004981"
    },
    {
        "type": "message",
        "user": "U045MBNTQ",
        "text": "ive been drinking milk every morning now",
        "ts": "1438364468.004982"
    },
    {
        "type": "message",
        "user": "U045MBNTQ",
        "text": "to make sure i dont get the shits",
        "ts": "1438364474.004983"
    },
    {
        "type": "message",
        "user": "U045MBNTQ",
        "text": "because of lactose intolerance.",
        "ts": "1438364477.004984"
    },
    {
        "type": "message",
        "user": "U046AEEDH",
        "text": "lel",
        "ts": "1438364585.004985"
    },
    {
        "type": "message",
        "user": "U045MBFTN",
        "text": "i overheard people in the break room saying how all fremont schools suck",
        "ts": "1438364654.004986"
    },
    {
        "type": "message",
        "user": "U045MBFTN",
        "text": "and that there are no good schools in the bay area",
        "ts": "1438364660.004987"
    },
    {
        "type": "message",
        "user": "U045MBNTQ",
        "text": "tell those bitches",
        "ts": "1438364709.004988"
    },
    {
        "type": "message",
        "user": "U045MBNTQ",
        "text": "to send their kids to harker",
        "ts": "1438364711.004989"
    },
    {
        "type": "message",
        "user": "U045MBNTQ",
        "text": "get all that privilege",
        "ts": "1438364717.004990"
    },
    {
        "type": "message",
        "user": "U045MBFTN",
        "text": "harker #1",
        "ts": "1438364916.004991"
    },
    {
        "type": "message",
        "user": "U046AEEDH",
        "text": "sup gooblers",
        "ts": "1438373645.004992"
    },
    {
        "type": "message",
        "user": "U045MBNTQ",
        "text": "hi novi",
        "ts": "1438373647.004993"
    },
    {
        "type": "message",
        "user": "U045MBNTQ",
        "text": ":simple_smile:",
        "ts": "1438373650.004994"
    },
    {
        "type": "message",
        "user": "U046AEEDH",
        "text": "how long did you wait?",
        "ts": "1438373658.004995"
    },
    {
        "type": "message",
        "user": "U046AEEDH",
        "text": "hours?",
        "ts": "1438373662.004996"
    },
    {
        "type": "message",
        "user": "U045MBNTQ",
        "text": "wut",
        "ts": "1438373663.004997"
    },
    {
        "type": "message",
        "user": "U045MBNTQ",
        "text": "i just thought it was about time to check on this tab",
        "ts": "1438373673.004998"
    },
    {
        "type": "message",
        "user": "U045MBNTQ",
        "text": "and saw you typing",
        "ts": "1438373675.004999"
    },
    {
        "type": "message",
        "user": "U045MBNTQ",
        "text": ":heart:",
        "ts": "1438373676.005000"
    },
    {
        "type": "message",
        "user": "U046AEEDH",
        "text": "market is gonna close in 15",
        "ts": "1438373695.005001"
    },
    {
        "type": "message",
        "user": "U046AEEDH",
        "text": "I can't test my stuff completely because they decided to do QA maintenence",
        "ts": "1438373708.005002"
    },
    {
        "type": "message",
        "user": "U045MBNTQ",
        "text": ":disappointed:",
        "ts": "1438373712.005003"
    },
    {
        "type": "message",
        "user": "U045MBNTQ",
        "text": "why they always gotta mess with you",
        "ts": "1438373717.005004"
    },
    {
        "type": "message",
        "user": "U046AEEDH",
        "text": "though I'm like 90% sure it works",
        "ts": "1438373721.005005"
    },
    {
        "type": "message",
        "user": "U046AEEDH",
        "text": "so idgaf",
        "ts": "1438373725.005006"
    },
    {
        "type": "message",
        "user": "U046AEEDH",
        "text": "I'll have it tested and pushed within 30 minutes of getting to my desk on Monday",
        "ts": "1438373738.005007"
    },
    {
        "type": "message",
        "user": "U046AEEDH",
        "text": "I just had a nice cup of coffee so I'm feeling gud",
        "ts": "1438373753.005008"
    },
    {
        "type": "message",
        "user": "U045MBNTQ",
        "text": "i wish",
        "ts": "1438373822.005009"
    },
    {
        "type": "message",
        "user": "U045MBNTQ",
        "text": "i could stop drinking coffee",
        "ts": "1438373825.005010"
    },
    {
        "type": "message",
        "user": "U045MBNTQ",
        "text": "but commuting for 3 hours a day",
        "ts": "1438373828.005011"
    },
    {
        "type": "message",
        "user": "U045MBNTQ",
        "text": "is just a no go",
        "ts": "1438373829.005012"
    },
    {
        "type": "message",
        "user": "U046AEEDH",
        "text": "just make sure you don't add any sugar in it",
        "ts": "1438373912.005013"
    },
    {
        "type": "message",
        "user": "U046AEEDH",
        "text": "and keep the cream and\/or milk to reasonable levels",
        "ts": "1438373921.005014"
    },
    {
        "type": "message",
        "user": "U045MBNTQ",
        "text": "uh",
        "ts": "1438373997.005015"
    },
    {
        "type": "message",
        "user": "U045MBNTQ",
        "text": "i just make my own pour overs",
        "ts": "1438374003.005016"
    },
    {
        "type": "message",
        "user": "U045MBNTQ",
        "text": "i always drink it black.",
        "ts": "1438374007.005017"
    },
    {
        "type": "message",
        "user": "U045MBNTQ",
        "text": "if you don't take it black",
        "ts": "1438374020.005018"
    },
    {
        "type": "message",
        "user": "U045MBNTQ",
        "text": "you lost a little bit of masculinity right then and there",
        "ts": "1438374026.005019"
    },
    {
        "type": "message",
        "user": "U046AEEDH",
        "text": "&gt; if you don't take it black",
        "ts": "1438374093.005020"
    },
    {
        "type": "message",
        "user": "U046AEEDH",
        "text": "&gt; Kelvin 2015",
        "ts": "1438374100.005021"
    },
    {
        "type": "message",
        "user": "U046AEEDH",
        "text": "&gt; lel ( \u0361\u00b0 \u035c\u0296 \u0361\u00b0)",
        "edited": {
            "user": "U046AEEDH",
            "ts": "1438374126.000000"
        },
        "ts": "1438374116.005022"
    },
    {
        "type": "message",
        "user": "U045MBNTQ",
        "text": ":simple_smile:",
        "ts": "1438374677.005024"
    },
    {
        "type": "message",
        "user": "U045MBNTQ",
        "text": "u know what i mean",
        "ts": "1438374679.005025"
    },
    {
        "type": "message",
        "user": "U045MBNTQ",
        "text": ":wink:",
        "ts": "1438374681.005026"
    },
    {
        "type": "message",
        "user": "U046AEEDH",
        "text": "you need some more brown in your life",
        "ts": "1438374875.005027"
    },
    {
        "type": "message",
        "user": "U046AEEDH",
        "text": "try having some mocha",
        "ts": "1438374888.005028"
    },
    {
        "type": "message",
        "user": "U046AEEDH",
        "text": ":simple_smile:",
        "ts": "1438374890.005029"
    },
    {
        "type": "message",
        "user": "U045MBNTQ",
        "text": "too much sugar",
        "ts": "1438374893.005030"
    },
    {
        "type": "message",
        "user": "U046AEEDH",
        "text": "if anything I hear it's too salty",
        "ts": "1438375982.005031"
    },
    {
        "type": "message",
        "user": "U046AEEDH",
        "text": "Lots of colorfully dressed sloots are in the city",
        "ts": "1438376821.005032"
    },
    {
        "type": "message",
        "user": "U046AEEDH",
        "text": "Lolla looks to be fun",
        "ts": "1438376826.005033"
    },
    {
        "type": "message",
        "user": "U045MBNTQ",
        "text": "are you going to",
        "ts": "1438376873.005034"
    },
    {
        "type": "message",
        "user": "U045MBNTQ",
        "text": "lollapalooza?",
        "ts": "1438376875.005035"
    },
    {
        "type": "message",
        "user": "U045MBNTQ",
        "text": ":disappointed:",
        "ts": "1438377826.005036"
    },
    {
        "type": "message",
        "user": "U046AEEDH",
        "text": "Nope",
        "ts": "1438377925.005037"
    },
    {
        "type": "message",
        "user": "U046AEEDH",
        "text": "Gotta go get my car fixed",
        "ts": "1438377930.005038"
    },
    {
        "type": "message",
        "user": "U046AEEDH",
        "text": "Plus I'm not 21 so my friends that would go would have more fun than me\/without me",
        "ts": "1438377949.005039"
    },
    {
        "type": "message",
        "user": "U045MBNTQ",
        "text": "oh is it this weekend?",
        "ts": "1438377956.005040"
    },
    {
        "type": "message",
        "user": "U045MBNTQ",
        "text": "oh it started today",
        "ts": "1438377975.005041"
    },
    {
        "type": "message",
        "user": "U045MBNTQ",
        "text": "lol",
        "ts": "1438377976.005042"
    },
    {
        "type": "message",
        "user": "U045MBNTQ",
        "text": "lollapalooza and outsidelands",
        "ts": "1438377980.005043"
    },
    {
        "type": "message",
        "user": "U045MBNTQ",
        "text": "one day apart",
        "ts": "1438377981.005044"
    },
    {
        "type": "message",
        "user": "U045MBNTQ",
        "text": "week*",
        "ts": "1438378082.005045"
    },
    {
        "type": "message",
        "user": "U045MBNTQ",
        "text": "hmm, they're pretty similar lol",
        "ts": "1438378098.005046"
    },
    {
        "type": "message",
        "user": "U046AEEDH",
        "text": "Yeah",
        "ts": "1438378172.005047"
    },
    {
        "type": "message",
        "user": "U046AEEDH",
        "text": "Lollla doesn't have the best artists this week",
        "ts": "1438378184.005048"
    },
    {
        "type": "message",
        "user": "U045MBNTQ",
        "text": "yeah",
        "ts": "1438378190.005049"
    },
    {
        "type": "message",
        "user": "U045MBNTQ",
        "text": "i think they're both pretty meh",
        "ts": "1438378194.005050"
    },
    {
        "type": "message",
        "user": "U045MBNTQ",
        "text": "so im not going to outsidelands",
        "ts": "1438378200.005051"
    },
    {
        "type": "message",
        "user": "U045MBNTQ",
        "text": "im going to one in vegas instead",
        "ts": "1438378206.005052"
    },
    {
        "type": "message",
        "user": "U045MBNTQ",
        "text": "i was drunk when i bought that ticket",
        "ts": "1438378210.005053"
    },
    {
        "type": "message",
        "user": "U045MBNTQ",
        "text": "but im committed now :confused:",
        "ts": "1438378216.005054"
    },
    {
        "type": "message",
        "user": "U046AEEDH",
        "text": "Nice, your drunk self writing checks you have to cash",
        "ts": "1438378480.005055"
    },
    {
        "type": "message",
        "user": "U045MBFTN",
        "text": "Damn novi you're missing out",
        "ts": "1438378537.005056"
    },
    {
        "type": "message",
        "user": "U045MBNTQ",
        "text": "novi you should go to the one in vegas",
        "ts": "1438378548.005057"
    },
    {
        "type": "message",
        "user": "U045MBNTQ",
        "text": "!!!",
        "ts": "1438378550.005058"
    },
    {
        "type": "message",
        "user": "U045MBNTQ",
        "text": "you'll be 21 at that point",
        "ts": "1438378554.005059"
    },
    {
        "type": "message",
        "user": "U03UNR40S",
        "text": "let's go to bonnaroo",
        "ts": "1438378613.005060"
    },
    {
        "type": "message",
        "user": "U045MBNTQ",
        "text": "damn",
        "ts": "1438378707.005061"
    },
    {
        "type": "message",
        "user": "U045MBNTQ",
        "text": "theres so much",
        "ts": "1438378708.005062"
    },
    {
        "type": "message",
        "user": "U045MBNTQ",
        "text": "although by like line 4-5",
        "ts": "1438378740.005063"
    },
    {
        "type": "message",
        "user": "U045MBNTQ",
        "text": "i don't know anyone.",
        "ts": "1438378742.005064"
    },
    {
        "type": "message",
        "user": "U03UNR40S",
        "text": "at bonnaroo?",
        "ts": "1438378756.005065"
    },
    {
        "type": "message",
        "user": "U046AEEDH",
        "text": "\u00bf",
        "ts": "1438378766.005066"
    },
    {
        "type": "message",
        "user": "U045MBNTQ",
        "text": "yeah",
        "ts": "1438378767.005067"
    },
    {
        "type": "message",
        "user": "U045MBNTQ",
        "text": "of course im talking about bonnaroo",
        "ts": "1438378773.005068"
    },
    {
        "type": "message",
        "user": "U03UNR40S",
        "text": "damn",
        "ts": "1438378776.005069"
    },
    {
        "type": "message",
        "user": "U03UNR40S",
        "text": "you never heard of twenty one pilots?",
        "ts": "1438378782.005070"
    },
    {
        "type": "message",
        "user": "U03UNR40S",
        "text": "tove lo",
        "ts": "1438378786.005071"
    },
    {
        "type": "message",
        "user": "U03UNR40S",
        "text": "odeza?",
        "ts": "1438378792.005072"
    },
    {
        "type": "message",
        "user": "U03UNR40S",
        "text": "odesza*",
        "ts": "1438378795.005073"
    },
    {
        "type": "message",
        "user": "U045MBNTQ",
        "text": "what line are they on",
        "ts": "1438378795.005074"
    },
    {
        "type": "message",
        "user": "U03UNR40S",
        "text": "g-eazy?",
        "ts": "1438378797.005075"
    },
    {
        "type": "message",
        "user": "U03UNR40S",
        "text": "twenty one pilots is like",
        "ts": "1438378806.005076"
    },
    {
        "type": "message",
        "user": "U045MBNTQ",
        "text": "ive heard of twenty one pilots",
        "ts": "1438378814.005077"
    },
    {
        "type": "message",
        "user": "U03UNR40S",
        "text": "7",
        "ts": "1438378814.005078"
    },
    {
        "type": "message",
        "user": "U045MBNTQ",
        "text": "and odesza",
        "ts": "1438378815.005079"
    },
    {
        "type": "message",
        "user": "U045MBNTQ",
        "text": "ive only heard of odesza",
        "ts": "1438378821.005080"
    },
    {
        "type": "message",
        "user": "U045MBNTQ",
        "text": "because of you",
        "ts": "1438378822.005081"
    },
    {
        "type": "message",
        "user": "U03UNR40S",
        "text": "odesza is like 10",
        "ts": "1438378828.005082"
    },
    {
        "type": "message",
        "user": "U045MBNTQ",
        "text": "i only know twenty one pilots",
        "ts": "1438378832.005083"
    },
    {
        "type": "message",
        "user": "U03UNR40S",
        "text": "same with tove lo",
        "ts": "1438378833.005084"
    },
    {
        "type": "message",
        "user": "U045MBNTQ",
        "text": "because they're going to life is beautiful",
        "ts": "1438378839.005085"
    },
    {
        "type": "message",
        "user": "U045MBNTQ",
        "text": "so ive listened to some of their stuff",
        "ts": "1438378843.005086"
    },
    {
        "type": "message",
        "user": "U03UNR40S",
        "text": "do you know g-eazy?",
        "ts": "1438378847.005087"
    },
    {
        "type": "message",
        "user": "U03UNR40S",
        "text": "awolnation?",
        "ts": "1438378852.005088"
    },
    {
        "type": "message",
        "user": "U045MBNTQ",
        "text": "i know awolnation",
        "ts": "1438378868.005089"
    },
    {
        "type": "message",
        "user": "U045MBNTQ",
        "text": "don't know g-eazy",
        "ts": "1438378870.005090"
    },
    {
        "type": "message",
        "user": "U045MBNTQ",
        "text": "damn tickets are 350?",
        "ts": "1438378873.005091"
    },
    {
        "type": "message",
        "user": "U03UNR40S",
        "text": "damn",
        "ts": "1438378874.005092"
    },
    {
        "type": "message",
        "user": "U045MBNTQ",
        "text": "thats a bit expensie",
        "ts": "1438378877.005093"
    },
    {
        "type": "message",
        "user": "U045MBNTQ",
        "text": "expensive*",
        "ts": "1438378879.005094"
    },
    {
        "type": "message",
        "user": "U03UNR40S",
        "text": "but he's a berkeley rapper!",
        "ts": "1438378879.005095"
    },
    {
        "type": "message",
        "user": "U03UNR40S",
        "text": "or i guess oakland",
        "ts": "1438378887.005096"
    },
    {
        "type": "message",
        "user": "U03UNR40S",
        "text": "but w\/e",
        "ts": "1438378888.005097"
    },
    {
        "type": "message",
        "user": "U03UNR40S",
        "text": "close enough",
        "ts": "1438378889.005098"
    },
    {
        "type": "message",
        "user": "U045MBNTQ",
        "text": "wait",
        "ts": "1438378893.005099"
    },
    {
        "type": "message",
        "user": "U045MBNTQ",
        "text": "this already passed",
        "ts": "1438378895.005100"
    },
    {
        "type": "message",
        "user": "U045MBNTQ",
        "text": "what the fuck kevin",
        "ts": "1438378897.005101"
    },
    {
        "type": "message",
        "user": "U03UNR40S",
        "text": "yeah i know lel",
        "ts": "1438378910.005102"
    },
    {
        "type": "message",
        "user": "U045MBNTQ",
        "text": ".......",
        "ts": "1438378913.005103"
    },
    {
        "type": "message",
        "user": "U045MBNTQ",
        "text": "wow",
        "ts": "1438378914.005104"
    },
    {
        "type": "message",
        "user": "U03UNR40S",
        "text": "damn they have",
        "ts": "1438378915.005105"
    },
    {
        "type": "message",
        "user": "U03UNR40S",
        "text": "so percussion!",
        "ts": "1438378918.005106"
    },
    {
        "type": "message",
        "user": "U03UNR40S",
        "text": "i saw them live!!!",
        "ts": "1438378920.005107"
    },
    {
        "type": "message",
        "user": "U045MBNTQ",
        "text": "i dont know any of these",
        "ts": "1438378924.005108"
    },
    {
        "type": "message",
        "user": "U045MBNTQ",
        "text": "this is the one im going to",
        "ts": "1438378941.005109"
    },
    {
        "type": "message",
        "user": "U045MBNTQ",
        "text": "<http:\/\/lineup.lifeisbeautiful.com\/>",
        "attachments": [
            {
                "title": "Life is Beautiful",
                "title_link": "http:\/\/lineup.lifeisbeautiful.com\/",
                "text": "See who's playing Life is Beautiful 2015, which of your friends are going, and pick your own favorites.",
                "fallback": "Life is Beautiful",
                "image_url": "http:\/\/lifeisbeautiful.com\/wp-content\/uploads\/2013\/06\/Heart_Logo_2014.jpg",
                "from_url": "http:\/\/lineup.lifeisbeautiful.com\/",
                "image_width": 282,
                "image_height": 250,
                "image_bytes": 77282,
                "id": 1
            }
        ],
        "ts": "1438378941.005110"
    },
    {
        "type": "message",
        "user": "U045MBNTQ",
        "text": "thats a pretty cool img",
        "ts": "1438378947.005112"
    },
    {
        "type": "message",
        "user": "U045MBNTQ",
        "text": "sup gary, off work already?",
        "ts": "1438378955.005113"
    },
    {
        "type": "message",
        "user": "U045MBNTQ",
        "text": "i c u online",
        "ts": "1438378961.005114"
    },
    {
        "type": "message",
        "user": "U03UNR40S",
        "text": "they also got x ambassadors, they were kinda popular",
        "ts": "1438378962.005115"
    },
    {
        "type": "message",
        "user": "U03UNR40S",
        "text": "gary",
        "ts": "1438379176.005116"
    },
    {
        "type": "message",
        "user": "U03UNR40S",
        "text": "let's go to this",
        "ts": "1438379178.005117"
    },
    {
        "type": "message",
        "user": "U03UNR40S",
        "text": "<http:\/\/www.northcoastfestival.com\/>",
        "ts": "1438379178.005118"
    },
    {
        "type": "message",
        "user": "U045MBNTQ",
        "text": "garys gonna be there 9\/4-9\/6?",
        "ts": "1438379919.005119"
    },
    {
        "type": "message",
        "user": "U03UNR40S",
        "text": "no i'm gonna be in the bay then",
        "ts": "1438379928.005120"
    },
    {
        "type": "message",
        "user": "U03UNR40S",
        "text": ":^(",
        "ts": "1438379928.005121"
    },
    {
        "type": "message",
        "user": "U045MBNTQ",
        "text": "wut",
        "ts": "1438379953.005122"
    },
    {
        "type": "message",
        "user": "U045MBNTQ",
        "text": "how long are you coming back for",
        "ts": "1438379957.005123"
    },
    {
        "type": "message",
        "user": "U03UNR40S",
        "text": "4 days",
        "ts": "1438380029.005124"
    },
    {
        "type": "message",
        "user": "U045MBNTQ",
        "text": "labor day?",
        "ts": "1438380119.005125"
    },
    {
        "type": "message",
        "user": "U045MBNTQ",
        "text": "or after labor day",
        "ts": "1438380122.005126"
    },
    {
        "type": "message",
        "user": "U03UNR40S",
        "text": "9\/3-9\/8",
        "ts": "1438380190.005127"
    },
    {
        "type": "message",
        "user": "U03UNR40S",
        "text": "but prolly not gonna be in the bay",
        "ts": "1438380193.005128"
    },
    {
        "type": "message",
        "user": "U03UNR40S",
        "text": "the last two days",
        "ts": "1438380195.005129"
    },
    {
        "type": "message",
        "user": "U045MBNTQ",
        "text": "wow",
        "ts": "1438380228.005130"
    },
    {
        "type": "message",
        "user": "U045MBNTQ",
        "text": "2 k00l",
        "ts": "1438380230.005131"
    },
    {
        "type": "message",
        "user": "U045MBNTQ",
        "text": "where you going",
        "ts": "1438380231.005132"
    },
    {
        "type": "message",
        "user": "U03UNR40S",
        "text": "LA",
        "ts": "1438380242.005133"
    },
    {
        "type": "message",
        "user": "U045MBNTQ",
        "text": "waow",
        "ts": "1438380252.005134"
    },
    {
        "type": "message",
        "user": "U045MBNTQ",
        "text": "are you flying back from LA?",
        "ts": "1438380258.005135"
    },
    {
        "type": "message",
        "user": "U03UNR40S",
        "text": "yeah",
        "ts": "1438380263.005136"
    },
    {
        "type": "message",
        "user": "U045MBNTQ",
        "text": "LA -&gt; Chicago",
        "ts": "1438380265.005137"
    },
    {
        "type": "message",
        "user": "U045MBNTQ",
        "text": "ahhh",
        "ts": "1438380265.005138"
    },
    {
        "type": "message",
        "user": "U045MBNTQ",
        "text": "damn",
        "ts": "1438380267.005139"
    },
    {
        "type": "message",
        "user": "U045MBNTQ",
        "text": "2 legit",
        "ts": "1438380269.005140"
    },
    {
        "type": "message",
        "user": "U045MBNTQ",
        "text": "you have a car?",
        "ts": "1438380273.005141"
    },
    {
        "type": "message",
        "user": "U03UNR40S",
        "text": "chris and thomas",
        "ts": "1438380278.005142"
    },
    {
        "type": "message",
        "user": "U045MBNTQ",
        "text": "they're driving",
        "ts": "1438380284.005143"
    },
    {
        "type": "message",
        "user": "U045MBNTQ",
        "text": "from bay area to LA?",
        "ts": "1438380289.005144"
    },
    {
        "type": "message",
        "user": "U03UNR40S",
        "text": "yah",
        "ts": "1438380292.005145"
    },
    {
        "type": "message",
        "user": "U03UNR40S",
        "text": "or at least one of them",
        "ts": "1438380295.005146"
    },
    {
        "type": "message",
        "user": "U045MBNTQ",
        "text": "shet",
        "ts": "1438380296.005147"
    },
    {
        "type": "message",
        "user": "U03UNR40S",
        "text": "right <@U045MFQ3C> ????",
        "ts": "1438380299.005148"
    },
    {
        "type": "message",
        "user": "U045MFQ3C",
        "text": "<@U03UNR40S>: no fuck you",
        "ts": "1438380309.005149"
    },
    {
        "type": "message",
        "user": "U046PCGDV",
        "text": "music festivals suck :^)",
        "ts": "1438380311.005150"
    },
    {
        "type": "message",
        "user": "U03UNR40S",
        "text": "fuck all of you",
        "ts": "1438380315.005151"
    },
    {
        "type": "message",
        "user": "U045MBNTQ",
        "text": "thats the spirit thomas",
        "ts": "1438380317.005152"
    },
    {
        "type": "message",
        "user": "U045MBNTQ",
        "text": "im so tired",
        "ts": "1438380327.005153"
    },
    {
        "type": "message",
        "user": "U045MBNTQ",
        "text": "i just want to take a nap",
        "ts": "1438380329.005154"
    },
    {
        "type": "message",
        "user": "U045MBNTQ",
        "text": "i have to drink",
        "ts": "1438380346.005155"
    },
    {
        "type": "message",
        "user": "U045MBNTQ",
        "text": "in an hour",
        "ts": "1438380347.005156"
    },
    {
        "type": "message",
        "user": "U045MBNTQ",
        "text": "fuuuu",
        "ts": "1438380348.005157"
    },
    {
        "type": "message",
        "user": "U045MBNTQ",
        "text": "fuck i give up on life",
        "edited": {
            "user": "U045MBNTQ",
            "ts": "1438380704.000000"
        },
        "ts": "1438380698.005158"
    },
    {
        "type": "message",
        "user": "U045MBNTQ",
        "text": "i need that coffee",
        "ts": "1438380707.005160"
    },
    {
        "type": "message",
        "subtype": "file_share",
        "text": "<@U045MBNTQ|reyarch> uploaded a file: <https:\/\/599usd.slack.com\/files\/reyarch\/F08EXE2DB\/slack_for_ios_upload.jpg|Slack for iOS Upload>",
        "file": {
            "id": "F08EXE2DB",
            "created": 1438380814,
            "timestamp": 1438380814,
            "name": "Slack for iOS Upload.jpg",
            "title": "Slack for iOS Upload",
            "mimetype": "image\/jpeg",
            "filetype": "jpg",
            "pretty_type": "JPEG",
            "user": "U045MBNTQ",
            "editable": false,
            "size": 299833,
            "mode": "hosted",
            "is_external": false,
            "external_type": "",
            "is_public": true,
            "public_url_shared": false,
            "display_as_bot": false,
            "username": "",
            "url": "https:\/\/slack-files.com\/files-pub\/T03UNR40Q-F08EXE2DB-aa0d211c1f\/slack_for_ios_upload.jpg",
            "url_download": "https:\/\/slack-files.com\/files-pub\/T03UNR40Q-F08EXE2DB-aa0d211c1f\/download\/slack_for_ios_upload.jpg",
            "url_private": "https:\/\/files.slack.com\/files-pri\/T03UNR40Q-F08EXE2DB\/slack_for_ios_upload.jpg",
            "url_private_download": "https:\/\/files.slack.com\/files-pri\/T03UNR40Q-F08EXE2DB\/download\/slack_for_ios_upload.jpg",
            "thumb_64": "https:\/\/slack-files.com\/files-tmb\/T03UNR40Q-F08EXE2DB-ac4b078d7b\/slack_for_ios_upload_64.jpg",
            "thumb_80": "https:\/\/slack-files.com\/files-tmb\/T03UNR40Q-F08EXE2DB-ac4b078d7b\/slack_for_ios_upload_80.jpg",
            "thumb_360": "https:\/\/slack-files.com\/files-tmb\/T03UNR40Q-F08EXE2DB-ac4b078d7b\/slack_for_ios_upload_360.jpg",
            "thumb_360_w": 270,
            "thumb_360_h": 360,
            "thumb_480": "https:\/\/slack-files.com\/files-tmb\/T03UNR40Q-F08EXE2DB-ac4b078d7b\/slack_for_ios_upload_480.jpg",
            "thumb_480_w": 360,
            "thumb_480_h": 480,
            "thumb_160": "https:\/\/slack-files.com\/files-tmb\/T03UNR40Q-F08EXE2DB-ac4b078d7b\/slack_for_ios_upload_160.jpg",
            "thumb_720": "https:\/\/slack-files.com\/files-tmb\/T03UNR40Q-F08EXE2DB-ac4b078d7b\/slack_for_ios_upload_720.jpg",
            "thumb_720_w": 540,
            "thumb_720_h": 720,
            "thumb_960": "https:\/\/slack-files.com\/files-tmb\/T03UNR40Q-F08EXE2DB-ac4b078d7b\/slack_for_ios_upload_960.jpg",
            "thumb_960_w": 720,
            "thumb_960_h": 960,
            "thumb_1024": "https:\/\/slack-files.com\/files-tmb\/T03UNR40Q-F08EXE2DB-ac4b078d7b\/slack_for_ios_upload_1024.jpg",
            "thumb_1024_w": 768,
            "thumb_1024_h": 1024,
            "image_exif_rotation": 1,
            "permalink": "https:\/\/599usd.slack.com\/files\/reyarch\/F08EXE2DB\/slack_for_ios_upload.jpg",
            "permalink_public": "https:\/\/slack-files.com\/T03UNR40Q-F08EXE2DB-aa0d211c1f",
            "channels": [
                "C03UNR412"
            ],
            "groups": [],
            "ims": [],
            "comments_count": 0
        },
        "user": "U045MBNTQ",
        "upload": true,
        "display_as_bot": false,
        "username": "<@U045MBNTQ|reyarch>",
        "bot_id": null,
        "ts": "1438380819.005161"
    },
    {
        "type": "message",
        "user": "U04NBCC1U",
        "text": "<@U03UNR40S>: i hear megas bus had pretty nice rates",
        "ts": "1438381693.005162"
    },
    {
        "type": "message",
        "user": "U04NBCC1U",
        "text": "or the dart bus",
        "ts": "1438381697.005163"
    },
    {
        "type": "message",
        "user": "U04NBCC1U",
        "text": "there is also always amtrak",
        "ts": "1438381703.005164"
    },
    {
        "type": "message",
        "user": "U045MBFTN",
        "text": "fak",
        "ts": "1438381917.005165"
    },
    {
        "type": "message",
        "user": "U045MBFTN",
        "text": "my witholding is wrong",
        "ts": "1438381922.005166"
    },
    {
        "type": "message",
        "user": "U045MBFTN",
        "text": "whelp, more money to buy $SQRE",
        "ts": "1438381927.005167"
    },
    {
        "type": "message",
        "user": "U04NBCC1U",
        "text": "did u put too many exceptions?",
        "ts": "1438381936.005168"
    },
    {
        "type": "message",
        "user": "U045MBFTN",
        "text": "no",
        "ts": "1438381943.005169"
    },
    {
        "type": "message",
        "user": "U04NBCC1U",
        "text": "u mean more money for $enva?",
        "ts": "1438381946.005170"
    },
    {
        "type": "message",
        "user": "U045MBFTN",
        "text": "they didn't take out my 401k contribution",
        "ts": "1438381950.005171"
    },
    {
        "type": "message",
        "user": "U045MBNTQ",
        "text": "lol it takes",
        "ts": "1438381956.005172"
    },
    {
        "type": "message",
        "user": "U045MBFTN",
        "text": "and CA took too much tax money from me",
        "ts": "1438381956.005173"
    },
    {
        "type": "message",
        "user": "U045MBNTQ",
        "text": "a month",
        "ts": "1438381957.005174"
    },
    {
        "type": "message",
        "user": "U045MBFTN",
        "text": "!!!",
        "ts": "1438381962.005175"
    },
    {
        "type": "message",
        "user": "U045MBFTN",
        "text": "I'm getting scammed!",
        "ts": "1438381965.005176"
    },
    {
        "type": "message",
        "user": "U04NBCC1U",
        "text": "damn",
        "ts": "1438381969.005177"
    },
    {
        "type": "message",
        "user": "U045MBNTQ",
        "text": "for it to actually work",
        "ts": "1438381971.005178"
    },
    {
        "type": "message",
        "user": "U045MBFTN",
        "text": "I already updated my stuff on Fidelity's website",
        "ts": "1438381971.005179"
    },
    {
        "type": "message",
        "user": "U04NBCC1U",
        "text": "#occupysactown",
        "ts": "1438381977.005180"
    },
    {
        "type": "message",
        "user": "U045MBFTN",
        "text": "#noincometax",
        "ts": "1438381984.005181"
    },
    {
        "type": "message",
        "user": "U045MBFTN",
        "text": "#trump2016",
        "ts": "1438381987.005182"
    },
    {
        "type": "message",
        "user": "U04NBCC1U",
        "text": "!!!!",
        "ts": "1438382037.005183"
    },
    {
        "type": "message",
        "user": "U04NBCC1U",
        "text": "fk",
        "ts": "1438382041.005184"
    },
    {
        "type": "message",
        "user": "U04NBCC1U",
        "text": "i have to report at 8 on monday",
        "ts": "1438382046.005185"
    },
    {
        "type": "message",
        "user": "U04NBCC1U",
        "text": "pls help",
        "ts": "1438382047.005186"
    },
    {
        "type": "message",
        "user": "U045MBFTN",
        "text": "wait so when they start taking money",
        "ts": "1438382159.005187"
    },
    {
        "type": "message",
        "user": "U045MBFTN",
        "text": "will my tax witholdings automatically scale down?",
        "ts": "1438382168.005188"
    },
    {
        "type": "message",
        "user": "U045MBNTQ",
        "text": "huh",
        "ts": "1438382227.005189"
    },
    {
        "type": "message",
        "user": "U045MBNTQ",
        "text": "fuuuuuuuuuuuu",
        "ts": "1438384515.005190"
    },
    {
        "type": "message",
        "user": "U045MBNTQ",
        "text": "my ruby mine is super fucked up",
        "ts": "1438384519.005191"
    },
    {
        "type": "message",
        "user": "U03UNR40S",
        "text": "rekt",
        "ts": "1438385000.005192"
    },
    {
        "type": "message",
        "user": "U03UNR40S",
        "text": "ruby mine sux",
        "ts": "1438385001.005193"
    },
    {
        "type": "message",
        "user": "U03UNR40S",
        "text": ":^)",
        "ts": "1438385002.005194"
    },
    {
        "type": "message",
        "user": "U045MBNTQ",
        "text": "sigh",
        "ts": "1438385030.005195"
    },
    {
        "type": "message",
        "user": "U045MBNTQ",
        "text": "pls",
        "ts": "1438385032.005196"
    },
    {
        "type": "message",
        "user": "U045MBNTQ",
        "text": "what do i do",
        "ts": "1438385036.005197"
    },
    {
        "type": "message",
        "user": "U045MBNTQ",
        "text": "plsplspls",
        "ts": "1438385037.005198"
    },
    {
        "type": "message",
        "user": "U045T05DE",
        "text": "Git reset --hard HEAD origin\/master",
        "ts": "1438385203.005199"
    },
    {
        "type": "message",
        "user": "U045MBNTQ",
        "text": "...",
        "ts": "1438385217.005200"
    },
    {
        "type": "message",
        "user": "U045MBNTQ",
        "text": "im not retarded",
        "ts": "1438385222.005201"
    },
    {
        "type": "message",
        "user": "U045T05DE",
        "text": "Did you commit your stuff before you got fucked?",
        "ts": "1438385324.005202"
    },
    {
        "type": "message",
        "user": "U045MBNTQ",
        "text": "no",
        "ts": "1438385333.005203"
    },
    {
        "type": "message",
        "user": "U045T05DE",
        "text": "Lel",
        "ts": "1438385337.005204"
    },
    {
        "type": "message",
        "user": "U045MBNTQ",
        "text": "when i said fucked up",
        "ts": "1438385342.005205"
    },
    {
        "type": "message",
        "user": "U045MBNTQ",
        "text": "i meant",
        "ts": "1438385343.005206"
    },
    {
        "type": "message",
        "user": "U045MBNTQ",
        "text": "my configs",
        "ts": "1438385344.005207"
    },
    {
        "type": "message",
        "user": "U045MBNTQ",
        "text": "are fucked up",
        "ts": "1438385345.005208"
    },
    {
        "type": "message",
        "user": "U045MBNTQ",
        "text": "like",
        "ts": "1438385346.005209"
    },
    {
        "type": "message",
        "user": "U045MBNTQ",
        "text": "but its only for rspec",
        "ts": "1438385349.005210"
    },
    {
        "type": "message",
        "user": "U045MBNTQ",
        "text": "everything else works fine.",
        "ts": "1438385353.005211"
    },
    {
        "type": "message",
        "user": "U045T05DE",
        "text": "I don't any ruby stuff",
        "ts": "1438385358.005212"
    },
    {
        "type": "message",
        "user": "U045MBNTQ",
        "text": "but rspec when i have a do block",
        "ts": "1438385359.005213"
    },
    {
        "type": "message",
        "user": "U045MBNTQ",
        "text": "it doesn't respect the indentations",
        "ts": "1438385362.005214"
    },
    {
        "type": "message",
        "user": "U045T05DE",
        "text": "Lol wut",
        "ts": "1438385367.005215"
    },
    {
        "type": "message",
        "user": "U045MBNTQ",
        "text": "when it makes the end",
        "ts": "1438385369.005216"
    },
    {
        "type": "message",
        "user": "U045MBNTQ",
        "text": "yeah",
        "ts": "1438385369.005217"
    },
    {
        "type": "message",
        "user": "U045MBNTQ",
        "text": "fuck rubymine",
        "ts": "1438385371.005218"
    },
    {
        "type": "message",
        "user": "U045MBNTQ",
        "text": "maybe i should just be like kevin",
        "ts": "1438385374.005219"
    },
    {
        "type": "message",
        "user": "U045MBNTQ",
        "text": "and use vim",
        "ts": "1438385377.005220"
    },
    {
        "type": "message",
        "user": "U045T05DE",
        "text": "Sounds pretty real lol",
        "ts": "1438385379.005221"
    },
    {
        "type": "message",
        "user": "U045T05DE",
        "text": "Use sublime be",
        "ts": "1438385388.005222"
    },
    {
        "type": "message",
        "user": "U045MBNTQ",
        "text": "its lowering my productivity",
        "ts": "1438385390.005223"
    },
    {
        "type": "message",
        "user": "U045MBNTQ",
        "text": "im complaining about it here",
        "ts": "1438385395.005224"
    },
    {
        "type": "message",
        "user": "U045MBNTQ",
        "text": "shil when do you get in the office everyday",
        "ts": "1438385423.005225"
    },
    {
        "type": "message",
        "user": "U03UNR40S",
        "text": "he doesn't",
        "ts": "1438385437.005226"
    },
    {
        "type": "message",
        "user": "U03UNR40S",
        "text": "he's permanently WFH :disappointed:",
        "ts": "1438385442.005227"
    },
    {
        "type": "message",
        "user": "U045MBNTQ",
        "text": "perfect",
        "ts": "1438385449.005228"
    },
    {
        "type": "message",
        "user": "U045MBNTQ",
        "text": "when i visit",
        "ts": "1438385458.005229"
    },
    {
        "type": "message",
        "user": "U045T05DE",
        "text": "Like 7:30 7:45",
        "ts": "1438385459.005230"
    },
    {
        "type": "message",
        "user": "U045MBNTQ",
        "text": "we're getting wasted every night",
        "ts": "1438385462.005231"
    },
    {
        "type": "message",
        "user": "U045MBNTQ",
        "text": ":simple_smile:",
        "ts": "1438385464.005232"
    },
    {
        "type": "message",
        "user": "U045T05DE",
        "text": "Yeh",
        "ts": "1438385465.005233"
    },
    {
        "type": "message",
        "user": "U045MBNTQ",
        "text": "yee",
        "ts": "1438385470.005234"
    },
    {
        "type": "message",
        "user": "U045MBNTQ",
        "text": "lets do it",
        "ts": "1438385473.005235"
    },
    {
        "type": "message",
        "user": "U045MBNTQ",
        "text": "do you guys have internet",
        "ts": "1438385478.005236"
    },
    {
        "type": "message",
        "user": "U045MBNTQ",
        "text": "good internet",
        "ts": "1438385480.005237"
    },
    {
        "type": "message",
        "user": "U045MBNTQ",
        "text": "like can i do work at your apartment",
        "ts": "1438385484.005238"
    },
    {
        "type": "message",
        "user": "U045T05DE",
        "text": "We probably will lol",
        "ts": "1438385486.005239"
    },
    {
        "type": "message",
        "user": "U045MBNTQ",
        "text": "when you live with kevin",
        "ts": "1438385487.005240"
    },
    {
        "type": "message",
        "user": "U03UNR40S",
        "text": "I'll try to get you the best, Kelvin!",
        "edited": {
            "user": "U03UNR40S",
            "ts": "1438386017.000000"
        },
        "ts": "1438386008.005241"
    },
    {
        "type": "message",
        "user": "U045MBNTQ",
        "text": ":heart:",
        "ts": "1438386016.005243"
    },
    {
        "type": "message",
        "user": "U045MBNTQ",
        "text": "yesss",
        "ts": "1438386018.005245"
    },
    {
        "type": "message",
        "user": "U045MBNTQ",
        "text": "could i borrow a monitor too?",
        "ts": "1438386024.005246"
    },
    {
        "type": "message",
        "user": "U03UNR40S",
        "text": "actually",
        "ts": "1438386039.005247"
    },
    {
        "type": "message",
        "user": "U03UNR40S",
        "text": "how about we just find a 4 bedroom apartment?",
        "ts": "1438386049.005248"
    },
    {
        "type": "message",
        "user": "U03UNR40S",
        "text": "and then you just live here?",
        "ts": "1438386053.005249"
    },
    {
        "type": "message",
        "user": "U03UNR40S",
        "text": ":simple_smile:",
        "ts": "1438386054.005250"
    },
    {
        "type": "message",
        "user": "U045MBNTQ",
        "text": "uhhhhh",
        "ts": "1438386085.005251"
    },
    {
        "type": "message",
        "user": "U046AEEDH",
        "text": "Hyessss",
        "ts": "1438386087.005252"
    },
    {
        "type": "message",
        "user": "U045MBNTQ",
        "text": "if you can pay me the same amount",
        "ts": "1438386096.005253"
    },
    {
        "type": "message",
        "user": "U045MBNTQ",
        "text": ":simple_smile:",
        "ts": "1438386099.005254"
    },
    {
        "type": "message",
        "user": "U03UNR40S",
        "text": "i don't pay you",
        "ts": "1438386106.005255"
    },
    {
        "type": "message",
        "user": "U03UNR40S",
        "text": "square pays you",
        "ts": "1438386108.005256"
    },
    {
        "type": "message",
        "user": "U03UNR40S",
        "text": "to WFH",
        "ts": "1438386109.005257"
    },
    {
        "type": "message",
        "user": "U03UNR40S",
        "text": ":simple_smile:",
        "ts": "1438386110.005258"
    },
    {
        "type": "message",
        "user": "U045MBNTQ",
        "text": "we don't have a chicago office........",
        "ts": "1438386121.005259"
    },
    {
        "type": "message",
        "user": "U03UNR40S",
        "text": "yeah",
        "ts": "1438386126.005260"
    },
    {
        "type": "message",
        "user": "U03UNR40S",
        "text": "that's why you WFH in Chicago",
        "ts": "1438386130.005261"
    },
    {
        "type": "message",
        "user": "U03UNR40S",
        "text": "the real office is in SF",
        "ts": "1438386134.005262"
    },
    {
        "type": "message",
        "user": "U03UNR40S",
        "text": "no big",
        "ts": "1438386135.005263"
    },
    {
        "type": "message",
        "user": "U045MBNTQ",
        "text": "i can't do that",
        "ts": "1438386141.005264"
    },
    {
        "type": "message",
        "user": "U03UNR40S",
        "text": "yeah you can, i bet Jack thinks your the most invaluable employee at the office",
        "ts": "1438386157.005265"
    },
    {
        "type": "message",
        "user": "U03UNR40S",
        "text": "can't get rid of you",
        "ts": "1438386160.005266"
    },
    {
        "type": "message",
        "user": "U045MBNTQ",
        "text": "im invaluable?",
        "ts": "1438386174.005267"
    },
    {
        "type": "message",
        "user": "U03UNR40S",
        "text": "yeah",
        "ts": "1438386177.005268"
    },
    {
        "type": "message",
        "user": "U045MBNTQ",
        "text": "so im not valuable",
        "ts": "1438386177.005269"
    },
    {
        "type": "message",
        "user": "U045MBNTQ",
        "text": ":disappointed:",
        "ts": "1438386178.005270"
    },
    {
        "type": "message",
        "user": "U03UNR40S",
        "text": ":disappointed:",
        "ts": "1438386183.005271"
    },
    {
        "type": "message",
        "user": "U03UNR40S",
        "text": "<http:\/\/puu.sh\/jkJiz\/1d3a3ec7fc.png>",
        "attachments": [
            {
                "fallback": "579x269px image",
                "image_url": "http:\/\/puu.sh\/jkJiz\/1d3a3ec7fc.png",
                "image_width": 579,
                "image_height": 269,
                "image_bytes": 12588,
                "from_url": "http:\/\/puu.sh\/jkJiz\/1d3a3ec7fc.png",
                "id": 1
            }
        ],
        "ts": "1438386220.005272"
    },
    {
        "type": "message",
        "user": "U045MBNTQ",
        "text": "im gonna get fired",
        "ts": "1438386259.005274"
    },
    {
        "type": "message",
        "user": "U045MBNTQ",
        "text": "why dont you all come to sf",
        "ts": "1438386265.005275"
    },
    {
        "type": "message",
        "user": "U045MBNTQ",
        "text": "jk",
        "ts": "1438386266.005276"
    },
    {
        "type": "message",
        "user": "U045MBNTQ",
        "text": "lets all go to ny",
        "ts": "1438386268.005277"
    },
    {
        "type": "message",
        "user": "U045MBNTQ",
        "text": "at least its not called the second city :simple_smile:",
        "ts": "1438386747.005278"
    },
    {
        "type": "message",
        "user": "U03UNR40S",
        "text": ":^(",
        "ts": "1438386756.005279"
    },
    {
        "type": "message",
        "user": "U045MBNTQ",
        "text": "its okay",
        "ts": "1438386779.005280"
    },
    {
        "type": "message",
        "user": "U045MBNTQ",
        "text": "you guys have a cool name",
        "ts": "1438386782.005281"
    },
    {
        "type": "message",
        "user": "U045MBNTQ",
        "text": "the windy city",
        "ts": "1438386783.005282"
    },
    {
        "type": "message",
        "user": "U045MBNTQ",
        "text": "sf doesn't  have any nicknames",
        "edited": {
            "user": "U045MBNTQ",
            "ts": "1438386802.000000"
        },
        "ts": "1438386792.005283"
    },
    {
        "type": "message",
        "user": "U045MBNTQ",
        "text": ":disappointed:",
        "ts": "1438386810.005285"
    },
    {
        "type": "message",
        "user": "U045T05DE",
        "text": "Americas butthole",
        "ts": "1438386817.005286"
    },
    {
        "type": "message",
        "user": "U045MBNTQ",
        "text": "nope",
        "ts": "1438386835.005287"
    },
    {
        "type": "message",
        "user": "U03UNR40S",
        "text": "damn",
        "ts": "1438386839.005288"
    },
    {
        "type": "message",
        "user": "U03UNR40S",
        "text": "you guys have",
        "ts": "1438386841.005289"
    },
    {
        "type": "message",
        "user": "U03UNR40S",
        "text": "_The City by the Bay_",
        "ts": "1438386846.005290"
    },
    {
        "type": "message",
        "user": "U03UNR40S",
        "text": "and",
        "ts": "1438386848.005291"
    },
    {
        "type": "message",
        "user": "U03UNR40S",
        "text": "_Fog City_",
        "ts": "1438386851.005292"
    },
    {
        "type": "message",
        "user": "U03UNR40S",
        "text": "and",
        "ts": "1438386852.005293"
    },
    {
        "type": "message",
        "user": "U03UNR40S",
        "text": "_San Fran_",
        "ts": "1438386855.005294"
    },
    {
        "type": "message",
        "user": "U03UNR40S",
        "text": "and",
        "ts": "1438386856.005295"
    },
    {
        "type": "message",
        "user": "U03UNR40S",
        "text": "_Frisco_",
        "ts": "1438386858.005296"
    },
    {
        "type": "message",
        "user": "U03UNR40S",
        "text": ":simple_smile:",
        "ts": "1438386858.005297"
    },
    {
        "type": "message",
        "user": "U045T05DE",
        "text": "FOG CITY",
        "ts": "1438386866.005298"
    },
    {
        "type": "message",
        "user": "U03UNR40S",
        "text": "_The City that Knows How_",
        "ts": "1438386868.005299"
    },
    {
        "type": "message",
        "user": "U03UNR40S",
        "text": "_Baghdad by the Bay_",
        "ts": "1438386875.005300"
    },
    {
        "type": "message",
        "user": "U045MBNTQ",
        "text": "ive never heard anyone",
        "ts": "1438386876.005301"
    },
    {
        "type": "message",
        "user": "U045MBNTQ",
        "text": "call it any of those",
        "ts": "1438386877.005302"
    },
    {
        "type": "message",
        "user": "U03UNR40S",
        "text": "_The Paris of the West_",
        "ts": "1438386880.005303"
    },
    {
        "type": "message",
        "user": "U045MBNTQ",
        "text": "except out of towners calling it frisco or san fran",
        "ts": "1438386886.005304"
    },
    {
        "type": "message",
        "user": "U045MBNTQ",
        "text": "_*shudders*_",
        "edited": {
            "user": "U045MBNTQ",
            "ts": "1438386893.000000"
        },
        "ts": "1438386888.005305"
    },
    {
        "type": "message",
        "user": "U03UNR40S",
        "text": "which one makes you shudder more",
        "ts": "1438386896.005307"
    },
    {
        "type": "message",
        "user": "U045MBNTQ",
        "text": "just",
        "ts": "1438386898.005308"
    },
    {
        "type": "message",
        "user": "U045MBNTQ",
        "text": "ew",
        "ts": "1438386898.005309"
    },
    {
        "type": "message",
        "user": "U045MBNTQ",
        "text": "frisco",
        "ts": "1438386900.005310"
    },
    {
        "type": "message",
        "user": "U045MBNTQ",
        "text": "easily.",
        "ts": "1438386901.005311"
    },
    {
        "type": "message",
        "user": "U03UNR40S",
        "text": "_Frisco_ or _ San Fran_",
        "ts": "1438386902.005312"
    },
    {
        "type": "message",
        "user": "U03UNR40S",
        "text": "nice",
        "ts": "1438386903.005313"
    },
    {
        "type": "message",
        "user": "U03UNR40S",
        "text": ":simple_smile:",
        "ts": "1438386903.005314"
    },
    {
        "type": "message",
        "user": "U045MBNTQ",
        "text": "cmon",
        "ts": "1438386910.005315"
    },
    {
        "type": "message",
        "user": "U045MBNTQ",
        "text": "which would you",
        "ts": "1438386913.005316"
    },
    {
        "type": "message",
        "user": "U045MBNTQ",
        "text": "shudder at more",
        "ts": "1438386914.005317"
    },
    {
        "type": "message",
        "user": "U045MBNTQ",
        "text": "we have a better motto than you guys though",
        "ts": "1438386924.005318"
    },
    {
        "type": "message",
        "user": "U045MBNTQ",
        "text": "_Urbs in Horto_",
        "ts": "1438386931.005319"
    },
    {
        "type": "message",
        "user": "U045MBNTQ",
        "text": "lel",
        "ts": "1438386932.005320"
    },
    {
        "type": "message",
        "user": "U03UNR40S",
        "text": "damn",
        "ts": "1438386952.005321"
    },
    {
        "type": "message",
        "user": "U03UNR40S",
        "text": "your guys' motto is just 2 cool",
        "ts": "1438386957.005322"
    },
    {
        "type": "message",
        "user": "U045MBNTQ",
        "text": "_*WE DO NOT SOW*_",
        "edited": {
            "user": "U045MBNTQ",
            "ts": "1438386978.000000"
        },
        "ts": "1438386975.005323"
    },
    {
        "type": "message",
        "user": "U03UNR40S",
        "text": "shil",
        "ts": "1438387021.005325"
    },
    {
        "type": "message",
        "user": "U03UNR40S",
        "text": "how many years until Chicago turns into Detroit",
        "ts": "1438387028.005326"
    },
    {
        "type": "message",
        "user": "U03UNR40S",
        "text": "?",
        "ts": "1438387029.005327"
    },
    {
        "type": "message",
        "user": "U045MBNTQ",
        "text": "you guys are too cool though",
        "ts": "1438387080.005328"
    },
    {
        "type": "message",
        "user": "U045MBNTQ",
        "text": "your motto is in latin",
        "ts": "1438387082.005329"
    },
    {
        "type": "message",
        "user": "U045MBNTQ",
        "text": "ours is in spanish :disappointed:",
        "ts": "1438387084.005330"
    },
    {
        "type": "message",
        "user": "U045T05DE",
        "text": "Gimme a couple to flash crash all the major options exchanges",
        "ts": "1438387106.005331"
    },
    {
        "type": "message",
        "user": "U045MBNTQ",
        "text": "then move to ny?",
        "ts": "1438387134.005332"
    },
    {
        "type": "message",
        "user": "U03UNR40S",
        "text": "cause SF is for beaners :^)",
        "ts": "1438387137.005333"
    },
    {
        "type": "message",
        "user": "U045MBNTQ",
        "text": "where we all can chill",
        "ts": "1438387138.005334"
    },
    {
        "type": "message",
        "user": "U045MBNTQ",
        "text": "and drink all night",
        "ts": "1438387142.005335"
    },
    {
        "type": "message",
        "user": "U045MBNTQ",
        "text": "and still get home",
        "ts": "1438387145.005336"
    },
    {
        "type": "message",
        "user": "U03UNR40S",
        "text": "damn",
        "ts": "1438387145.005337"
    },
    {
        "type": "message",
        "user": "U045MBNTQ",
        "text": "on the subway",
        "ts": "1438387148.005338"
    },
    {
        "type": "message",
        "user": "U03UNR40S",
        "text": "why is SF so shit kelvin",
        "ts": "1438387148.005339"
    },
    {
        "type": "message",
        "user": "U045MBNTQ",
        "text": "even at 4 am",
        "ts": "1438387149.005340"
    },
    {
        "type": "message",
        "user": "U03UNR40S",
        "text": "Chicago got destroyed in 1871",
        "ts": "1438387155.005341"
    },
    {
        "type": "message",
        "user": "U03UNR40S",
        "text": "and rebuilt itself nicely",
        "ts": "1438387160.005342"
    },
    {
        "type": "message",
        "user": "U03UNR40S",
        "text": "but SF got destroyed too in 1906",
        "ts": "1438387167.005343"
    },
    {
        "type": "message",
        "user": "U03UNR40S",
        "text": "and is still shit",
        "ts": "1438387169.005344"
    },
    {
        "type": "message",
        "user": "U03UNR40S",
        "text": ":^(",
        "ts": "1438387170.005345"
    },
    {
        "type": "message",
        "user": "U045MBNTQ",
        "text": "we need",
        "ts": "1438387175.005346"
    },
    {
        "type": "message",
        "user": "U045MBNTQ",
        "text": "another fire.",
        "ts": "1438387176.005347"
    },
    {
        "type": "message",
        "user": "U03UNR40S",
        "text": "yeah",
        "ts": "1438387181.005348"
    },
    {
        "type": "message",
        "user": "U03UNR40S",
        "text": "cleanse SF of all the techies",
        "ts": "1438387184.005349"
    },
    {
        "type": "message",
        "user": "U03UNR40S",
        "text": ":^)",
        "ts": "1438387185.005350"
    },
    {
        "type": "message",
        "user": "U045MBNTQ",
        "text": ":fire::fire::fire::fire::fire::fire::fire::fire::fire::fire::fire::fire::fire::fire:",
        "ts": "1438387188.005351"
    },
    {
        "type": "message",
        "user": "U045MBNTQ",
        "text": "then i can move",
        "ts": "1438387197.005352"
    },
    {
        "type": "message",
        "user": "U03UNR40S",
        "text": "<https:\/\/en.wikipedia.org\/wiki\/1906_San_Francisco_earthquake#\/media\/File:Sfearthquake.jpg>",
        "ts": "1438387252.005353"
    },
    {
        "type": "message",
        "user": "U03UNR40S",
        "text": "market st got rekt :disappointed:",
        "ts": "1438387255.005354"
    },
    {
        "type": "message",
        "user": "U045MBNTQ",
        "text": "it looks better it did",
        "ts": "1438387273.005355"
    },
    {
        "type": "message",
        "user": "U045MBNTQ",
        "text": "back then",
        "ts": "1438387273.005356"
    },
    {
        "type": "message",
        "user": "U045MBNTQ",
        "text": "than it does now",
        "ts": "1438387276.005357"
    },
    {
        "type": "message",
        "user": "U03UNR40S",
        "text": "huehuehuehue",
        "ts": "1438387280.005358"
    },
    {
        "type": "message",
        "user": "U045MBNTQ",
        "text": "seriously though",
        "ts": "1438387290.005359"
    },
    {
        "type": "message",
        "user": "U045MBNTQ",
        "text": "just look ati t",
        "ts": "1438387291.005360"
    },
    {
        "type": "message",
        "user": "U03UNR40S",
        "text": "maybe if you instigated another city-wide fire",
        "ts": "1438387293.005361"
    },
    {
        "type": "message",
        "user": "U045MBNTQ",
        "text": "on google street view",
        "ts": "1438387296.005362"
    },
    {
        "type": "message",
        "user": "U03UNR40S",
        "text": "you can live in a nice camp like this! <https:\/\/en.wikipedia.org\/wiki\/1906_San_Francisco_earthquake#\/media\/File:Row_of_shacks.jpg>",
        "ts": "1438387298.005363"
    },
    {
        "type": "message",
        "user": "U03UNR40S",
        "text": "all of this was destroyed in the Great Chicago Fire :disappointed: <https:\/\/upload.wikimedia.org\/wikipedia\/commons\/3\/3a\/Great_Chicago_Fire_map_with_starting_point.jpg>",
        "attachments": [
            {
                "fallback": "3588x5382px image",
                "image_url": "https:\/\/upload.wikimedia.org\/wikipedia\/commons\/3\/3a\/Great_Chicago_Fire_map_with_starting_point.jpg",
                "image_width": 3588,
                "image_height": 5382,
                "image_bytes": 3625644,
                "from_url": "https:\/\/upload.wikimedia.org\/wikipedia\/commons\/3\/3a\/Great_Chicago_Fire_map_with_starting_point.jpg",
                "id": 1
            }
        ],
        "ts": "1438387406.005364"
    },
    {
        "type": "message",
        "user": "U045MBNTQ",
        "text": "did you know",
        "ts": "1438387466.005366"
    },
    {
        "type": "message",
        "user": "U045MBNTQ",
        "text": "the only reason why",
        "ts": "1438387468.005367"
    },
    {
        "type": "message",
        "user": "U045MBNTQ",
        "text": "bank of america became a real bank",
        "ts": "1438387471.005368"
    },
    {
        "type": "message",
        "user": "U045MBNTQ",
        "text": "was because of the sf fire",
        "ts": "1438387475.005369"
    },
    {
        "type": "message",
        "user": "U03UNR40S",
        "text": "hmm? tell me more",
        "ts": "1438387531.005370"
    },
    {
        "type": "message",
        "user": "U045MBNTQ",
        "text": "<https:\/\/en.wikipedia.org\/wiki\/Bank_of_Italy_(United_States)>",
        "ts": "1438387555.005371"
    },
    {
        "type": "message",
        "user": "U03UNR40S",
        "text": "damn",
        "ts": "1438387588.005372"
    },
    {
        "type": "message",
        "user": "U045MBNTQ",
        "text": "&gt;When the 1906 San Francisco earthquake struck, Giannini was able to save all deposits out of the bank building and away from the fires. Because San Francisco's banks were in smoldering ruins and unable to open their vaults, Giannini was able to use the rescued funds to commence lending within a few days of the disaster. From a makeshift desk consisting of a few planks over two barrels, he lent money to those who wished to rebuild.",
        "ts": "1438387589.005373"
    },
    {
        "type": "message",
        "user": "U03UNR40S",
        "text": "why didn't :enova: offer loans to rebuilding San Franciscans?",
        "ts": "1438387599.005374"
    },
    {
        "type": "message",
        "user": "U03UNR40S",
        "text": ":^)",
        "ts": "1438387600.005375"
    },
    {
        "type": "message",
        "user": "U045MBNTQ",
        "text": "....",
        "ts": "1438387629.005376"
    },
    {
        "type": "message",
        "user": "U045MBFTN",
        "text": "Frisco is okay if you're a 80s rapper",
        "ts": "1438387785.005377"
    },
    {
        "type": "message",
        "user": "U045MBFTN",
        "text": "but SF has no rap game :simple_smile:",
        "ts": "1438387795.005378"
    },
    {
        "type": "message",
        "user": "U045MBFTN",
        "text": "it's all techies now",
        "ts": "1438387798.005379"
    },
    {
        "type": "message",
        "user": "U045MBNTQ",
        "text": "what do you even rhyme with frisco?",
        "ts": "1438387894.005380"
    },
    {
        "type": "message",
        "user": "U045MBNTQ",
        "text": "cisco?",
        "ts": "1438387894.005381"
    },
    {
        "type": "message",
        "user": "U045MBNTQ",
        "text": "pisco",
        "ts": "1438387899.005382"
    },
    {
        "type": "message",
        "user": "U045MBNTQ",
        "text": "nabisco",
        "ts": "1438387903.005383"
    },
    {
        "type": "message",
        "user": "U045MBNTQ",
        "text": "crisco",
        "ts": "1438387908.005384"
    },
    {
        "type": "message",
        "user": "U03UNR40S",
        "text": "disco",
        "ts": "1438387935.005385"
    },
    {
        "type": "message",
        "user": "U045MBNTQ",
        "text": "yeah there isn't shit",
        "ts": "1438388028.005386"
    },
    {
        "type": "message",
        "user": "U045MBNTQ",
        "text": "that rhymes",
        "ts": "1438388029.005387"
    },
    {
        "type": "message",
        "user": "U03UNR40S",
        "text": "damn dude",
        "ts": "1438388083.005388"
    },
    {
        "type": "message",
        "user": "U03UNR40S",
        "text": "<https:\/\/upload.wikimedia.org\/wikipedia\/commons\/1\/1b\/Attributed_to_George_N._Barnard_-_Untitled_%28Chicago_after_the_Chicago_Fire%29_-_Google_Art_Project.jpg>",
        "attachments": [
            {
                "fallback": "6312x976px image",
                "image_url": "https:\/\/upload.wikimedia.org\/wikipedia\/commons\/1\/1b\/Attributed_to_George_N._Barnard_-_Untitled_%28Chicago_after_the_Chicago_Fire%29_-_Google_Art_Project.jpg",
                "image_width": 6312,
                "image_height": 976,
                "image_bytes": 1791467,
                "from_url": "https:\/\/upload.wikimedia.org\/wikipedia\/commons\/1\/1b\/Attributed_to_George_N._Barnard_-_Untitled_%28Chicago_after_the_Chicago_Fire%29_-_Google_Art_Project.jpg",
                "id": 1
            }
        ],
        "ts": "1438388085.005389"
    },
    {
        "type": "message",
        "user": "U03UNR40S",
        "text": "chicago got rekt",
        "ts": "1438388086.005391"
    },
    {
        "type": "message",
        "user": "U03UNR40S",
        "text": "also rappers don't rhyme anymore",
        "ts": "1438388090.005392"
    },
    {
        "type": "message",
        "user": "U03UNR40S",
        "text": "just look at 2chainz",
        "ts": "1438388093.005393"
    },
    {
        "type": "message",
        "user": "U03UNR40S",
        "text": "i mean the rhymes are so lame",
        "ts": "1438388097.005394"
    },
    {
        "type": "message",
        "user": "U03UNR40S",
        "text": "&gt;She got a big booty",
        "ts": "1438388105.005395"
    },
    {
        "type": "message",
        "user": "U03UNR40S",
        "text": "&gt;So I call her big booty",
        "ts": "1438388109.005396"
    },
    {
        "type": "message",
        "user": "U045MBNTQ",
        "text": "how is that rekt",
        "edited": {
            "user": "U045MBNTQ",
            "ts": "1438388126.000000"
        },
        "ts": "1438388120.005397"
    },
    {
        "type": "message",
        "user": "U045MBNTQ",
        "text": "that looks taller than sf",
        "ts": "1438388128.005399"
    },
    {
        "type": "message",
        "user": "U045MBNTQ",
        "text": "today",
        "ts": "1438388129.005400"
    },
    {
        "type": "message",
        "user": "U03UNR40S",
        "text": "redo your guys' zoning regulations plx",
        "ts": "1438388166.005401"
    },
    {
        "type": "message",
        "user": "U045MBNTQ",
        "text": ":disappointed:",
        "ts": "1438388301.005402"
    },
    {
        "type": "message",
        "user": "U045MBNTQ",
        "text": "i told you",
        "ts": "1438388303.005403"
    },
    {
        "type": "message",
        "user": "U045MBNTQ",
        "text": "shittiest city",
        "ts": "1438388304.005404"
    },
    {
        "type": "message",
        "user": "U045MBNTQ",
        "text": "in the us",
        "ts": "1438388305.005405"
    },
    {
        "type": "message",
        "user": "U03UNR40S",
        "text": "chicago has pretty shitty zoning regulations too",
        "ts": "1438388321.005406"
    },
    {
        "type": "message",
        "user": "U03UNR40S",
        "text": "but not as bad as SF",
        "ts": "1438388327.005407"
    },
    {
        "type": "message",
        "user": "U045MBNTQ",
        "text": "lets all move to ny",
        "ts": "1438388497.005408"
    },
    {
        "type": "message",
        "user": "U045MBNTQ",
        "text": ":simple_smile:",
        "ts": "1438388497.005409"
    },
    {
        "type": "message",
        "user": "U045MBNTQ",
        "text": ":wink:",
        "ts": "1438388512.005410"
    },
    {
        "type": "message",
        "user": "U045MBNTQ",
        "text": ":apple:",
        "ts": "1438388520.005411"
    },
    {
        "type": "message",
        "user": "U045MBNTQ",
        "text": ":yum:",
        "ts": "1438388532.005412"
    },
    {
        "type": "message",
        "user": "U04NBCC1U",
        "text": "gais",
        "ts": "1438392346.005413"
    },
    {
        "type": "message",
        "user": "U04NBCC1U",
        "text": "i feel left out",
        "ts": "1438392348.005414"
    },
    {
        "type": "message",
        "user": "U04NBCC1U",
        "text": "pls all of you",
        "ts": "1438392350.005415"
    },
    {
        "type": "message",
        "user": "U04NBCC1U",
        "text": "move to the city of angels",
        "ts": "1438392356.005416"
    },
    {
        "type": "message",
        "user": "U04NBCC1U",
        "text": "or hollywood",
        "ts": "1438392361.005417"
    },
    {
        "type": "message",
        "user": "U04NBCC1U",
        "text": "<@U03UNR40S>: kevin pls move to LA",
        "ts": "1438392384.005418"
    },
    {
        "type": "message",
        "user": "U04NBCC1U",
        "text": "and WFM to enova",
        "ts": "1438392387.005419"
    },
    {
        "type": "message",
        "user": "U03UNR40S",
        "text": "Damn",
        "ts": "1438392449.005420"
    },
    {
        "type": "message",
        "user": "U03UNR40S",
        "text": "It's okay LA sux ",
        "ts": "1438392459.005421"
    },
    {
        "type": "message",
        "user": "U03UNR40S",
        "text": ":^)",
        "ts": "1438392462.005422"
    },
    {
        "type": "message",
        "user": "U04NBCC1U",
        "text": ":((",
        "ts": "1438392468.005423"
    },
    {
        "type": "message",
        "user": "U04NBCC1U",
        "text": "i'm psure LA sux less than Chicago or SF",
        "ts": "1438392476.005424"
    },
    {
        "type": "message",
        "user": "U03UNR40S",
        "text": "It's fine bb you got Thomas ",
        "ts": "1438392478.005425"
    },
    {
        "type": "message",
        "user": "U04NBCC1U",
        "text": "LA is  of most important in CA",
        "ts": "1438392485.005426"
    },
    {
        "type": "message",
        "user": "U04NBCC1U",
        "text": "Thomas isn't even rlly in LA",
        "ts": "1438392496.005427"
    },
    {
        "type": "message",
        "user": "U04NBCC1U",
        "text": "hes in the valley",
        "ts": "1438392502.005428"
    },
    {
        "type": "message",
        "user": "U04NBCC1U",
        "text": "we also have the happiest place on earth",
        "ts": "1438392580.005429"
    }
]