[
    {
        "type": "message",
        "user": "U045MBNTQ",
        "text": "why is this a dead channel :disappointed:",
        "ts": "1436903064.000005"
    },
    {
        "type": "message",
        "user": "U03UNR40S",
        "text": ":disappointed:",
        "ts": "1436903069.000006"
    },
    {
        "type": "message",
        "user": "U045MBNTQ",
        "text": "pls",
        "ts": "1436903072.000007"
    },
    {
        "type": "message",
        "user": "U045MBNTQ",
        "text": "i want to get my autismo going",
        "ts": "1436903077.000008"
    }
]